nillion_python_helpers/__init__.py
nillion_python_helpers/client.py
nillion_python_helpers/keypath.py
nillion_python_helpers/payments.py
nillion_python_helpers-0.3.0.dist-info/LICENSE
nillion_python_helpers-0.3.0.dist-info/METADATA
nillion_python_helpers-0.3.0.dist-info/WHEEL
nillion_python_helpers-0.3.0.dist-info/RECORD
