Metadata-Version: 2.1
Name: nillion-python-helpers
Version: 0.3.0
Summary: 
Author: José Cabrero-Holgueras
Author-email: jose.cabrero@nillion.com
Requires-Python: >=3.10,<4.0
Classifier: Programming Language :: Python :: 3
Classifier: Programming Language :: Python :: 3.10
Classifier: Programming Language :: Python :: 3.11
Classifier: Programming Language :: Python :: 3.12
Requires-Dist: cosmpy (>=0.9.2,<0.10.0)
Requires-Dist: py-nillion-client (>=0.6.0,<0.7.0)
Requires-Dist: pytest-asyncio (>=0.23.7,<0.24.0)
Requires-Dist: python-dotenv (==1.0.0)
